{"pixiv_pic": [{"name": "119227578", "path": "./pixiv/2024-06-03-14-01-31/119227578.jpg", "index": 0, "user": "\u7d05\u30b7\u30e3\u30b1\uff20\u304a\u4ed5\u4e8b\u52df\u96c6\u4e2d", "ext": ".jpg"}, {"name": "119224984", "path": "./pixiv/2024-06-03-14-01-31/119224984.jpg", "index": 1, "user": "\u30a6\u30e9", "ext": ".jpg"}, {"name": "119259267", "path": "./pixiv/2024-06-03-14-01-31/119259267.jpg", "index": 2, "user": "\u7adc\u5d0e\u3044\u3061", "ext": ".jpg"}, {"name": "119248705", "path": "./pixiv/2024-06-03-14-01-31/119248705.jpg", "index": 3, "user": "\u9e4c\u9e51", "ext": ".jpg"}, {"name": "119225116", "path": "./pixiv/2024-06-03-14-01-31/119225116.png", "index": 4, "user": "\u85e4\u3061\u3087\u3053\uff08\u85e4\u539f\uff09", "ext": ".png"}, {"name": "119225816", "path": "./pixiv/2024-06-03-14-01-31/119225816.png", "index": 5, "user": "\u307f\u3059\u307f", "ext": ".png"}, {"name": "119262720", "path": "./pixiv/2024-06-03-14-01-31/119262720.jpg", "index": 6, "user": "\u3089\u3044\u3089\u3063\u304f", "ext": ".jpg"}, {"name": "119225129", "path": "./pixiv/2024-06-03-14-01-31/119225129.jpg", "index": 7, "user": "\u30a2\u30b7\u30de222Ashima", "ext": ".jpg"}, {"name": "119258365", "path": "./pixiv/2024-06-03-14-01-31/119258365.jpg", "index": 8, "user": "yejji", "ext": ".jpg"}, {"name": "119233933", "path": "./pixiv/2024-06-03-14-01-31/119233933.jpg", "index": 9, "user": "SukeP\uff08\u3059\u3051\u3074\u30fc\uff09", "ext": ".jpg"}, {"name": "119247420", "path": "./pixiv/2024-06-03-14-01-31/119247420.png", "index": 10, "user": "\u305d\u3089\u306a\u306b\u3044\u308d", "ext": ".png"}, {"name": "119275191", "path": "./pixiv/2024-06-03-14-01-31/119275191.jpg", "index": 11, "user": "\u4f50\u5009\u304a\u308a\u3053@\u5358\u884c\u672c\u767a\u58f2\u4e2d", "ext": ".jpg"}, {"name": "119288849", "path": "./pixiv/2024-06-03-14-01-31/119288849.png", "index": 12, "user": "\u5927\u6d25", "ext": ".png"}, {"name": "119259712", "path": "./pixiv/2024-06-03-14-01-31/119259712.png", "index": 13, "user": "SP\u00b33p", "ext": ".png"}, {"name": "119227549", "path": "./pixiv/2024-06-03-14-01-31/119227549.jpg", "index": 14, "user": "\u30dd\u30c6\u30c8\u30eb\u30b9", "ext": ".jpg"}, {"name": "119245676", "path": "./pixiv/2024-06-03-14-01-31/119245676.jpg", "index": 15, "user": "\u9b3c\u9488\u8349", "ext": ".jpg"}, {"name": "119286096", "path": "./pixiv/2024-06-03-14-01-31/119286096.png", "index": 16, "user": "\u30c1\u30e3\u30a4", "ext": ".png"}, {"name": "119249145", "path": "./pixiv/2024-06-03-14-01-31/119249145.png", "index": 17, "user": "kiri", "ext": ".png"}, {"name": "119225168", "path": "./pixiv/2024-06-03-14-01-31/119225168.jpg", "index": 18, "user": "\u3053\u304f\u3068", "ext": ".jpg"}, {"name": "119260346", "path": "./pixiv/2024-06-03-14-01-31/119260346.jpg", "index": 19, "user": "\u5343\u7a2e\u307f\u306e\u308a@\u304a\u4ed5\u4e8b\u52df\u96c6\u4e2d", "ext": ".jpg"}, {"name": "119258477", "path": "./pixiv/2024-06-03-14-01-31/119258477.jpg", "index": 20, "user": "pottsness", "ext": ".jpg"}, {"name": "119256860", "path": "./pixiv/2024-06-03-14-01-31/119256860.png", "index": 21, "user": "\u9022\u7de8\u3044\u3042\u3080", "ext": ".png"}, {"name": "119237149", "path": "./pixiv/2024-06-03-14-01-31/119237149.jpg", "index": 22, "user": "\u6df5\u309b\u25c6\u65b0\u520a\u901a\u8ca9", "ext": ".jpg"}, {"name": "119246749", "path": "./pixiv/2024-06-03-14-01-31/119246749.png", "index": 23, "user": "PiPi", "ext": ".png"}, {"name": "119258670", "path": "./pixiv/2024-06-03-14-01-31/119258670.png", "index": 24, "user": "Re\u00b0", "ext": ".png"}, {"name": "119225155", "path": "./pixiv/2024-06-03-14-01-31/119225155.png", "index": 25, "user": "mell\u00b0@\u304a\u4ed5\u4e8b\u52df\u96c6\u4e2d", "ext": ".png"}, {"name": "119250869", "path": "./pixiv/2024-06-03-14-01-31/119250869.png", "index": 26, "user": "\u30c1\u30e3\u30a4", "ext": ".png"}, {"name": "119247439", "path": "./pixiv/2024-06-03-14-01-31/119247439.png", "index": 27, "user": "\u30df\u30ca\u30df", "ext": ".png"}, {"name": "119260063", "path": "./pixiv/2024-06-03-14-01-31/119260063.jpg", "index": 28, "user": "\u30ab\u30ea\u30de\u30ea\u30abCARIMARICA", "ext": ".jpg"}, {"name": "119271837", "path": "./pixiv/2024-06-03-14-01-31/119271837.png", "index": 29, "user": "\u3042\u3089\u3082\u3093", "ext": ".png"}, {"name": "119247867", "path": "./pixiv/2024-06-03-14-01-31/119247867.png", "index": 30, "user": "\u7d05\u6728\u6625", "ext": ".png"}, {"name": "119235201", "path": "./pixiv/2024-06-03-14-01-31/119235201.png", "index": 31, "user": "Nvl", "ext": ".png"}, {"name": "119225079", "path": "./pixiv/2024-06-03-14-01-31/119225079.jpg", "index": 32, "user": "yejji", "ext": ".jpg"}, {"name": "119260743", "path": "./pixiv/2024-06-03-14-01-31/119260743.png", "index": 33, "user": "A1u_", "ext": ".png"}, {"name": "119225232", "path": "./pixiv/2024-06-03-14-01-31/119225232.png", "index": 34, "user": "CORE", "ext": ".png"}, {"name": "119225053", "path": "./pixiv/2024-06-03-14-01-31/119225053.png", "index": 35, "user": "\u30da\u30b1\u3053", "ext": ".png"}, {"name": "119258429", "path": "./pixiv/2024-06-03-14-01-31/119258429.jpg", "index": 36, "user": "\u3057\u3050\u308c\u3046\u3044", "ext": ".jpg"}, {"name": "119247155", "path": "./pixiv/2024-06-03-14-01-31/119247155.jpg", "index": 37, "user": "\u30ce\u30fc\u30b3\u30d4\u30fc\u30e9\u30a4\u30c8\u30ac\u30fc\u30eb", "ext": ".jpg"}, {"name": "119225154", "path": "./pixiv/2024-06-03-14-01-31/119225154.jpg", "index": 38, "user": "\u3057\u3050\u308c\u3046\u3044", "ext": ".jpg"}, {"name": "119249437", "path": "./pixiv/2024-06-03-14-01-31/119249437.jpg", "index": 39, "user": "\u30ca\u30e9\u306a\u304d\u308a", "ext": ".jpg"}, {"name": "119257481", "path": "./pixiv/2024-06-03-14-01-31/119257481.jpg", "index": 40, "user": "\u306e\u3093", "ext": ".jpg"}, {"name": "119232545", "path": "./pixiv/2024-06-03-14-01-31/119232545.jpg", "index": 41, "user": "\u6f2b\u753b\u7d20\u6750\u5de5\u623f", "ext": ".jpg"}, {"name": "119225660", "path": "./pixiv/2024-06-03-14-01-31/119225660.jpg", "index": 42, "user": "\u54b2\u5d0e\u3055\u304d\uff50", "ext": ".jpg"}, {"name": "119292837", "path": "./pixiv/2024-06-03-14-01-31/119292837.png", "index": 43, "user": "\u3053\u305f\u308d\u3046", "ext": ".png"}, {"name": "119225117", "path": "./pixiv/2024-06-03-14-01-31/119225117.jpg", "index": 44, "user": "110", "ext": ".jpg"}, {"name": "119252189", "path": "./pixiv/2024-06-03-14-01-31/119252189.png", "index": 45, "user": "YHM", "ext": ".png"}, {"name": "119225068", "path": "./pixiv/2024-06-03-14-01-31/119225068.png", "index": 46, "user": "Say1HANa", "ext": ".png"}, {"name": "119258446", "path": "./pixiv/2024-06-03-14-01-31/119258446.jpg", "index": 47, "user": "\u6751\u30ab\u30eb\u30ad", "ext": ".jpg"}]}