{"pixiv_pic": [{"name": "119567817", "path": "./pixiv/2024-06-14-14-02-33/119567817.png", "index": 0, "user": "XilmO@\u5915\u672b", "ext": ".png"}, {"name": "119584586", "path": "./pixiv/2024-06-14-14-02-33/119584586.png", "index": 1, "user": "\u30dd\u30eb", "ext": ".png"}, {"name": "119572579", "path": "./pixiv/2024-06-14-14-02-33/119572579.jpg", "index": 2, "user": "\u8272\u5dee\u307b\u3066", "ext": ".jpg"}, {"name": "119559769", "path": "./pixiv/2024-06-14-14-02-33/119559769.jpg", "index": 3, "user": "\u304a\u306f\u304e", "ext": ".jpg"}, {"name": "119575098", "path": "./pixiv/2024-06-14-14-02-33/119575098.jpg", "index": 4, "user": "\u3081\u3070\u308b", "ext": ".jpg"}, {"name": "119584629", "path": "./pixiv/2024-06-14-14-02-33/119584629.jpg", "index": 5, "user": "\u5922\u30ce\u5185", "ext": ".jpg"}, {"name": "119557297", "path": "./pixiv/2024-06-14-14-02-33/119557297.png", "index": 6, "user": "\u723d\u3005", "ext": ".png"}, {"name": "119585962", "path": "./pixiv/2024-06-14-14-02-33/119585962.jpg", "index": 7, "user": "\u307e\u3076\u3057", "ext": ".jpg"}, {"name": "119557281", "path": "./pixiv/2024-06-14-14-02-33/119557281.jpg", "index": 8, "user": "\u30b9\u30b3\u30c3\u30c6\u30a3", "ext": ".jpg"}, {"name": "119585498", "path": "./pixiv/2024-06-14-14-02-33/119585498.png", "index": 9, "user": "\u30a2\u30a4\u30b9\u30b9", "ext": ".png"}, {"name": "119584588", "path": "./pixiv/2024-06-14-14-02-33/119584588.jpg", "index": 10, "user": "\u5922\u30ce\u5185", "ext": ".jpg"}, {"name": "119604931", "path": "./pixiv/2024-06-14-14-02-33/119604931.png", "index": 11, "user": "YHM", "ext": ".png"}, {"name": "119590519", "path": "./pixiv/2024-06-14-14-02-33/119590519.jpg", "index": 12, "user": "\u6f2b\u753b\u7d20\u6750\u5de5\u623f", "ext": ".jpg"}, {"name": "119579899", "path": "./pixiv/2024-06-14-14-02-33/119579899.jpg", "index": 13, "user": "\u6708\u6708\u9ce5\u4eba", "ext": ".jpg"}, {"name": "119584479", "path": "./pixiv/2024-06-14-14-02-33/119584479.jpg", "index": 14, "user": "Lifeline", "ext": ".jpg"}, {"name": "119580783", "path": "./pixiv/2024-06-14-14-02-33/119580783.png", "index": 15, "user": "\u3048\u3050\u3048\u3050", "ext": ".png"}, {"name": "119561139", "path": "./pixiv/2024-06-14-14-02-33/119561139.png", "index": 16, "user": "\u30cf\u30df\u30bf", "ext": ".png"}, {"name": "119594735", "path": "./pixiv/2024-06-14-14-02-33/119594735.png", "index": 17, "user": "\u4f11\u5ac1\u4e00\u6167", "ext": ".png"}, {"name": "119579799", "path": "./pixiv/2024-06-14-14-02-33/119579799.png", "index": 18, "user": "\u30c1\u30e3\u30a4", "ext": ".png"}, {"name": "119559509", "path": "./pixiv/2024-06-14-14-02-33/119559509.jpg", "index": 19, "user": "\u304a\u304a\u307f\u3084", "ext": ".jpg"}, {"name": "119584680", "path": "./pixiv/2024-06-14-14-02-33/119584680.jpg", "index": 20, "user": "\u4e45\u84bc\u7a79", "ext": ".jpg"}, {"name": "119557309", "path": "./pixiv/2024-06-14-14-02-33/119557309.jpg", "index": 21, "user": "\u304a\u306b\u306d\u3053", "ext": ".jpg"}, {"name": "119557313", "path": "./pixiv/2024-06-14-14-02-33/119557313.jpg", "index": 22, "user": "A_maru", "ext": ".jpg"}, {"name": "119570840", "path": "./pixiv/2024-06-14-14-02-33/119570840.jpg", "index": 23, "user": "\u5929\u7948Eric", "ext": ".jpg"}, {"name": "119557331", "path": "./pixiv/2024-06-14-14-02-33/119557331.png", "index": 24, "user": "allitell", "ext": ".png"}, {"name": "119558325", "path": "./pixiv/2024-06-14-14-02-33/119558325.jpg", "index": 25, "user": "\u30a6\u30e9", "ext": ".jpg"}, {"name": "119558012", "path": "./pixiv/2024-06-14-14-02-33/119558012.png", "index": 26, "user": "CORE", "ext": ".png"}, {"name": "119570877", "path": "./pixiv/2024-06-14-14-02-33/119570877.png", "index": 27, "user": "\u30b7\u30d1\u30bd", "ext": ".png"}, {"name": "119584630", "path": "./pixiv/2024-06-14-14-02-33/119584630.png", "index": 28, "user": "\u6885\u539f\u751f\uff08\u305b\u3044\uff09", "ext": ".png"}, {"name": "119580412", "path": "./pixiv/2024-06-14-14-02-33/119580412.jpg", "index": 29, "user": "\u30e1\u30a4\u30b8", "ext": ".jpg"}, {"name": "119558538", "path": "./pixiv/2024-06-14-14-02-33/119558538.jpg", "index": 30, "user": "catzz", "ext": ".jpg"}, {"name": "119566923", "path": "./pixiv/2024-06-14-14-02-33/119566923.png", "index": 31, "user": "\u3042\u304d", "ext": ".png"}, {"name": "119572253", "path": "./pixiv/2024-06-14-14-02-33/119572253.jpg", "index": 32, "user": "\u4f0a\u85e4\u3089\u307c", "ext": ".jpg"}, {"name": "119601450", "path": "./pixiv/2024-06-14-14-02-33/119601450.jpg", "index": 33, "user": "\u304b\u3067\u3043\u3002", "ext": ".jpg"}, {"name": "119557373", "path": "./pixiv/2024-06-14-14-02-33/119557373.png", "index": 34, "user": "\u30df\u30e7\u30ef", "ext": ".png"}, {"name": "119578238", "path": "./pixiv/2024-06-14-14-02-33/119578238.png", "index": 35, "user": "\u308f\u3044\u3082\u306b\u304f", "ext": ".png"}, {"name": "119579854", "path": "./pixiv/2024-06-14-14-02-33/119579854.jpg", "index": 36, "user": "Sakon04", "ext": ".jpg"}, {"name": "119583151", "path": "./pixiv/2024-06-14-14-02-33/119583151.png", "index": 37, "user": "\u30a2\u30ea\u30af\u30a4\u306e\u30a4\u30ab\u30af", "ext": ".png"}, {"name": "119585141", "path": "./pixiv/2024-06-14-14-02-33/119585141.jpg", "index": 38, "user": "\u77ac\u304f", "ext": ".jpg"}, {"name": "119585988", "path": "./pixiv/2024-06-14-14-02-33/119585988.jpg", "index": 39, "user": "\u5ddd\u5d0e", "ext": ".jpg"}, {"name": "119575138", "path": "./pixiv/2024-06-14-14-02-33/119575138.jpg", "index": 40, "user": "\u5df4\u838e\u5361_R", "ext": ".jpg"}, {"name": "119559886", "path": "./pixiv/2024-06-14-14-02-33/119559886.png", "index": 41, "user": "Bibimbub", "ext": ".png"}, {"name": "119557360", "path": "./pixiv/2024-06-14-14-02-33/119557360.jpg", "index": 42, "user": "\u96e8\u58f1\u7d75\u7a79", "ext": ".jpg"}, {"name": "119594240", "path": "./pixiv/2024-06-14-14-02-33/119594240.png", "index": 43, "user": "COCOball", "ext": ".png"}, {"name": "119560124", "path": "./pixiv/2024-06-14-14-02-33/119560124.jpg", "index": 44, "user": "\u306f\u308b", "ext": ".jpg"}, {"name": "119585707", "path": "./pixiv/2024-06-14-14-02-33/119585707.jpg", "index": 45, "user": "MARIA2ROSE", "ext": ".jpg"}]}